lion/__init__.py
lion/core/__init__.py
lion/core/_class_registry.py
lion/core/action/__init__.py
lion/core/action/action_manager.py
lion/core/action/base.py
lion/core/action/function_calling.py
lion/core/action/tool.py
lion/core/communication/__init__.py
lion/core/communication/action_request.py
lion/core/communication/action_response.py
lion/core/communication/assistant_response.py
lion/core/communication/base_mail.py
lion/core/communication/instruction.py
lion/core/communication/message.py
lion/core/communication/message_manager.py
lion/core/communication/system.py
lion/core/communication/utils.py
lion/core/forms/__init__.py
lion/core/forms/base.py
lion/core/forms/form.py
lion/core/forms/report.py
lion/core/forms/utils.py
lion/core/generic/__init__.py
lion/core/generic/component.py
lion/core/generic/edge.py
lion/core/generic/element.py
lion/core/generic/graph.py
lion/core/generic/log.py
lion/core/generic/log_manager.py
lion/core/generic/node.py
lion/core/generic/pile.py
lion/core/generic/progression.py
lion/core/generic/utils.py
lion/core/models/__init__.py
lion/core/models/base.py
lion/core/models/field_model.py
lion/core/models/new_model_params.py
lion/core/models/note.py
lion/core/models/operable_model.py
lion/core/models/schema_model.py
lion/core/session/__init__.py
lion/core/session/branch.py
lion/core/session/branch_mixins.py
lion/core/session/session.py
lion/core/typing/__init__.py
lion/core/typing/concepts.py
lion/core/typing/config.py
lion/core/typing/id.py
lion/core/typing/pydantic_.py
lion/core/typing/typing_.py
lion/integrations/__init__.py
lion/integrations/anthropic_/AnthropicModel.py
lion/integrations/anthropic_/AnthropicService.py
lion/integrations/anthropic_/__init__.py
lion/integrations/anthropic_/anthropic_max_output_token_data.yaml
lion/integrations/anthropic_/anthropic_price_data.yaml
lion/integrations/anthropic_/api_endpoints/__init__.py
lion/integrations/anthropic_/api_endpoints/api_request.py
lion_os-0.2.9.dist-info/LICENSE
lion_os-0.2.9.dist-info/METADATA
lion_os-0.2.9.dist-info/WHEEL
lion_os-0.2.9.dist-info/RECORD
