Metadata-Version: 2.1
Name: lion-os
Version: 0.2.9
Summary: 
Author: HaiyangLi
Author-email: quantocean.li@gmail.com
Requires-Python: >=3.11,<4.0
Classifier: Programming Language :: Python :: 3
Classifier: Programming Language :: Python :: 3.11
Classifier: Programming Language :: Python :: 3.12
Requires-Dist: litellm (>=1.50.0,<2.0.0)
Requires-Dist: matplotlib (>=3.0.0,<4.0.0)
Requires-Dist: networkx (>=3.0.0,<4.0.0)
Requires-Dist: pandas (>=2.0.0,<3.0.0)
Requires-Dist: pillow (>=11.0.0,<12.0.0)
Requires-Dist: python-dotenv (>=1.0.1,<2.0.0)
Requires-Dist: pyyaml (>=6.0.0,<7.0.0)
